gocept.selenium-7.1-py3.9-nspkg.pth
gocept/selenium/__init__.py
gocept/selenium/diff_txt.png
gocept/selenium/exp_txt.png
gocept/selenium/got_txt.png
gocept/selenium/screenshot.py
gocept/selenium/util.py
gocept/selenium/wd_selenese.py
gocept/selenium/webdriver.py
gocept/selenium/grok/__init__.py
gocept/selenium/grok/fixtures.py
gocept/selenium/grok/ftesting.zcml
gocept/selenium/grok/tests.py
gocept/selenium/plonetesting/__init__.py
gocept/selenium/plonetesting/testing.py
gocept/selenium/plonetesting/tests/__init__.py
gocept/selenium/plonetesting/tests/testing.zcml
gocept/selenium/plonetesting/tests/zope2/__init__.py
gocept/selenium/plonetesting/tests/zope2/test_zope2.py
gocept/selenium/scripts/__init__.py
gocept/selenium/scripts/converthtmltests.py
gocept/selenium/scripts/tests/__init__.py
gocept/selenium/scripts/tests/nocommands.html
gocept/selenium/scripts/tests/notitle.html
gocept/selenium/scripts/tests/plone3login.html
gocept/selenium/scripts/tests/test_converthtmltests.py
gocept/selenium/static/__init__.py
gocept/selenium/tests/__init__.py
gocept/selenium/tests/test_util.py
gocept/selenium/tests/test_wd_selenese.py
gocept/selenium/tests/test_webdriver.py
gocept/selenium/tests/fixture/__init__.py
gocept/selenium/tests/fixture/alert.html
gocept/selenium/tests/fixture/display-delay.html
gocept/selenium/tests/fixture/divs.html
gocept/selenium/tests/fixture/download.html
gocept/selenium/tests/fixture/empty-tag.html
gocept/selenium/tests/fixture/emtpy-tag.png
gocept/selenium/tests/fixture/example.pdf
gocept/selenium/tests/fixture/iframe.html
gocept/selenium/tests/fixture/intercepted.html
gocept/selenium/tests/fixture/launch-popup.html
gocept/selenium/tests/fixture/popup.html
gocept/selenium/tests/fixture/screenshot-chrome.png
gocept/selenium/tests/fixture/screenshot-edge.png
gocept/selenium/tests/fixture/screenshot.html
gocept/selenium/tests/fixture/screenshot.png
gocept/selenium/tests/fixture/screenshot_blocks.html
gocept/selenium/tests/fixture/screenshot_blocks.png
gocept.selenium-7.1.dist-info/LICENSE.txt
gocept.selenium-7.1.dist-info/METADATA
gocept.selenium-7.1.dist-info/WHEEL
gocept.selenium-7.1.dist-info/entry_points.txt
gocept.selenium-7.1.dist-info/namespace_packages.txt
gocept.selenium-7.1.dist-info/top_level.txt
gocept.selenium-7.1.dist-info/RECORD
