Metadata-Version: 2.1
Name: gocept.selenium
Version: 7.1
Summary: Test-friendly Python API for Selenium and integration with web application frameworks.
Home-page: https://goceptselenium.readthedocs.org/
Author: gocept and contributors
Author-email: mail@gocept.com
License: ZPL 2.1
Keywords: selenium zope grok plone pyramid pylons testing
Platform: UNKNOWN
Classifier: Development Status :: 6 - Mature
Classifier: Environment :: Console
Classifier: Environment :: Web Environment
Classifier: Framework :: BFG
Classifier: Framework :: Plone
Classifier: Framework :: Plone :: 5.2
Classifier: Framework :: Plone :: 5.3
Classifier: Framework :: Plone :: 6.0
Classifier: Framework :: Pylons
Classifier: Framework :: Pyramid
Classifier: Framework :: Zope :: 3
Classifier: Framework :: Zope :: 4
Classifier: Framework :: Zope :: 5
Classifier: Intended Audience :: Developers
Classifier: License :: OSI Approved
Classifier: License :: OSI Approved :: Zope Public License
Classifier: Natural Language :: English
Classifier: Operating System :: OS Independent
Classifier: Programming Language :: Python
Classifier: Programming Language :: Python :: 3
Classifier: Programming Language :: Python :: 3 :: Only
Classifier: Programming Language :: Python :: 3.7
Classifier: Programming Language :: Python :: 3.8
Classifier: Programming Language :: Python :: 3.9
Classifier: Programming Language :: Python :: Implementation
Classifier: Programming Language :: Python :: Implementation :: CPython
Classifier: Topic :: Software Development
Classifier: Topic :: Software Development :: Testing
Requires-Python: >=3.7, <4
License-File: LICENSE.txt
Requires-Dist: gocept.httpserverlayer (>=3)
Requires-Dist: httpagentparser
Requires-Dist: plone.testing (>=7.0)
Requires-Dist: selenium (>=4)
Requires-Dist: Pillow
Requires-Dist: setuptools
Requires-Dist: webdriver-manager
Provides-Extra: grok
Requires-Dist: gocept.httpserverlayer[zopeappwsgi] ; extra == 'grok'
Requires-Dist: zope.app.appsetup ; extra == 'grok'
Provides-Extra: plonetesting
Requires-Dist: gocept.httpserverlayer[plonetestingzope] ; extra == 'plonetesting'
Provides-Extra: screenshot
Requires-Dist: Pillow ; extra == 'screenshot'
